diceutils-0.3.6.dist-info/METADATA
diceutils-0.3.6.dist-info/WHEEL
diceutils-0.3.6.dist-info/licenses/LICENSE
diceutils/__init__.py
diceutils/cards.py
diceutils/charactors.py
diceutils/dicer.py
diceutils/exceptions.py
diceutils/logging.py
diceutils/parser.py
diceutils/renderer/__init__.py
diceutils/renderer/_models.py
diceutils/renderer/docx.py
diceutils/renderer/html.py
diceutils/renderer/pdf.py
diceutils/status.py
diceutils/utils.py
diceutils-0.3.6.dist-info/RECORD
