Metadata-Version: 2.1
Name: diceutils
Version: 0.3.6
Summary: 基于 Infini 标准的骰娘相关组件和工具类
Author-Email: 苏向夜 <fu050409@163.com>
License: GNU Affero General Public License v3
Classifier: Development Status :: 5 - Production/Stable
Classifier: Intended Audience :: Developers
Classifier: License :: OSI Approved :: GNU Affero General Public License v3
Classifier: Programming Language :: Python :: 3.12
Requires-Python: >=3.8
Requires-Dist: infini>=2.1.1
Requires-Dist: python-docx>=1.1.0
